README.md
setup.py
ASTen/__init__.py
ASTen.egg-info/PKG-INFO
ASTen.egg-info/SOURCES.txt
ASTen.egg-info/dependency_links.txt
ASTen.egg-info/requires.txt
ASTen.egg-info/top_level.txt