Metadata-Version: 2.4
Name: ASTen
Version: 0.1.0
Summary: A minimal PyTorch-like deep learning library
Author: ASTen Team
Classifier: Development Status :: 3 - Alpha
Classifier: Intended Audience :: Developers
Classifier: Topic :: Scientific/Engineering :: Artificial Intelligence
Classifier: Programming Language :: Python :: 3
Classifier: Programming Language :: C
Classifier: Programming Language :: C++
Requires-Python: >=3.7
Requires-Dist: numpy>=1.19.0
Requires-Dist: pybind11>=2.6.0
Dynamic: author
Dynamic: classifier
Dynamic: description
Dynamic: description-content-type
Dynamic: requires-dist
Dynamic: requires-python
Dynamic: summary
